risque/__init__.py
risque/client/__init__.py
risque/common/constants.py
risque/common/interfaces.py
risque/common/singleton.py
risque/common/task.py
risque/server/__init__.py
risque/server/handlers.py
risque/task_manager/__init__.py
risque-0.0.1.dist-info/LICENSE.txt
risque-0.0.1.dist-info/WHEEL
risque-0.0.1.dist-info/METADATA
risque-0.0.1.dist-info/RECORD
