Metadata-Version: 2.1
Name: risque
Version: 0.0.1
Summary: Risque is a task execution queue management package
Author-email: Sarthak Gambhir <sarthak.gambhir@outlook.com>
Classifier: License :: OSI Approved :: GNU General Public License v3 or later (GPLv3+)
